_pytidyhtml5.cpython-38-x86_64-linux-gnu.so
pytidyhtml5-2024.10.24.dist-info/top_level.txt
pytidyhtml5-2024.10.24.dist-info/RECORD
pytidyhtml5-2024.10.24.dist-info/LICENSE
pytidyhtml5-2024.10.24.dist-info/METADATA
pytidyhtml5-2024.10.24.dist-info/WHEEL
pytidyhtml5/_doc.py
pytidyhtml5/__init__.py
